{"dependencies":[{"name":"./index.js","dynamic":true}],"generated":{"html":"<!doctype html>\n<html>\n\n<head>\n  <meta charset=\"utf-8\">\n  <script defer=\"\" src=\"/dist/hyperapp-example.js\"></script>\n  <style>\n    html,\n    body {\n      font: 16px/1.3 'Helvetica Neue', helvetica, arial, sans-serif;\n    }\n\n    div,\n    button,\n    h1,\n    code {\n      animation: fadeIn 1s ease;\n    }\n\n    @keyframes fadeIn {\n      0% {\n        opacity: 0;\n        transform: translateX(-5px);\n      }\n    }\n  </style>\n</head>\n\n<body><div><h1>0</h1></div></body>\n\n</html>\n"},"hash":"2d120c71a06deb112cfff48369f10da6","cacheData":{}}